README
setup.cfg
setup.py
Python_PouchDB.egg-info/PKG-INFO
Python_PouchDB.egg-info/SOURCES.txt
Python_PouchDB.egg-info/dependency_links.txt
Python_PouchDB.egg-info/requires.txt
Python_PouchDB.egg-info/top_level.txt
pouchdb/__init__.py
pouchdb/bundle.js
pouchdb/context.py
pouchdb/info.py
pouchdb/mapping.py
pouchdb/objectstorage.py
pouchdb/utils.py
pouchdb/tests/__init__.py
pouchdb/tests/doctests.py
pouchdb/tests/main.py
pouchdb/tests/mapping.py
pouchdb/tests/objectstorage.py
pouchdb/tests/plugins.py
pouchdb/tests/utils.py