Metadata-Version: 1.1
Name: Python-PouchDB
Version: 0.4.1
Summary: A Python interface to PouchDB
Home-page: http://python-pouchdb.marten-de-vries.nl/
Author: Marten de Vries
Author-email: marten@openteacher.org
License: UNKNOWN
Platform: UNKNOWN
Classifier: Development Status :: 5 - Production/Stable
Classifier: Intended Audience :: Developers
Classifier: License :: OSI Approved :: Apache Software License
Classifier: Operating System :: MacOS :: MacOS X
Classifier: Operating System :: Microsoft :: Windows
Classifier: Operating System :: POSIX
Classifier: Programming Language :: JavaScript
Classifier: Programming Language :: Python :: 2
Classifier: Programming Language :: Python :: 3
Classifier: Topic :: Database
Classifier: Topic :: Software Development :: Libraries
